{
  "Adamczyk Andrzej": "PiS",
  "Adamczyk Rafał": "Lewica",
  "Adamowicz Piotr": "KO",
  "Ajchler Romuald": "Lewica",
  "Andruszkiewicz Adam": "PiS",
  "Andzel Waldemar": "PiS",
  "Aniśko Tomasz": "KO",
  "Ardanowski Jan Krzysztof": "PiS",
  "Arent Iwona": "PiS",
  "Ast Marek": "PiS",
  "Augustyn Urszula": "KO",
  "Aziewicz Tadeusz": "KO",
  "Babalski Zbigniew": "PiS",
  "Babinetz Piotr": "PiS",
  "Bartosik Ryszard": "PiS",
  "Bartoszewski Władysław Teofil": "KP",
  "Bartuś Barbara": "PiS",
  "Baszko Mieczysław": "PiS",
  "Bejda Paweł": "KP",
  "Berkowicz Konrad": "Konfederacja",
  "Biejat Magdalena": "Lewica",
  "Bielecki Jerzy": "PiS",
  "Biernacki Marek": "KP",
  "Bochenek Mateusz": "KO",
  "Bochenek Rafał": "PiS",
  "Borowczak Jerzy": "KO",
  "Borowiak Joanna": "PiS",
  "Bortniczuk Kamil": "PiS",
  "Borys Piotr": "KO",
  "Borys-Szopa Bożena": "PiS",
  "Bosak Krzysztof": "Konfederacja",
  "Braun Grzegorz": "Konfederacja",
  "Buda Waldemar": "PiS",
  "Budka Borys": "KO",
  "Bukowiec Stanisław": "PiS",
  "Burzyńska Lidia": "PiS",
  "Buż Wiesław": "Lewica",
  "Bąk Dariusz": "PiS",
  "Błaszczak Mariusz": "PiS",
  "Chmiel Małgorzata": "KO",
  "Chmielowiec Zbigniew": "PiS",
  "Choma Kazimierz": "PiS",
  "Chorosińska Dominika": "PiS",
  "Chrzan Tadeusz": "PiS",
  "Cicholska Anna Ewa": "PiS",
  "Cichoń Janusz": "KO",
  "Cieślak Michał": "PiS",
  "Cymański Tadeusz": "PiS",
  "Cyrański Adam": "KO",
  "Czarnecki Krzysztof": "PiS",
  "Czarnecki Przemysław": "PiS",
  "Czarnecki Witold": "PiS",
  "Czarnek Przemysław": "PiS",
  "Czartoryski Arkadiusz": "PiS",
  "Czarzasty Włodzimierz": "Lewica",
  "Czerniak Jacek": "Lewica",
  "Czernow Zofia": "KO",
  "Czerwińska Anita": "PiS",
  "Czochara Katarzyna": "PiS",
  "Czykwin Eugeniusz": "KO",
  "Dajczak Władysław": "PiS",
  "Dobrzyński Leszek": "PiS",
  "Dolata Zbigniew": "PiS",
  "Dolniak Barbara": "KO",
  "Dorywalski Bartłomiej": "PiS",
  "Drabek Przemysław": "PiS",
  "Duda Elżbieta": "PiS",
  "Duda Jan": "PiS",
  "Duszek Marcin": "PiS",
  "Dworczyk Michał": "PiS",
  "Dyduch Marek": "Lewica",
  "Dziambor Artur": "Konfederacja",
  "Dziedziczak Jan": "PiS",
  "Dziemianowicz-Bąk Agnieszka": "Lewica",
  "Dzikowski Waldy": "KO",
  "Dziuk Barbara": "PiS",
  "Dąbrowska-Banaszek Anna": "PiS",
  "Emilewicz Jadwiga": "PiS",
  "Fabisiak Joanna": "KO",
  "Falej Monika": "Lewica",
  "Fedak Jolanta": "KP",
  "Filiks Magdalena": "KO",
  "Filipiak Ewa": "PiS",
  "Fogiel Radosław": "PiS",
  "Frydrych Joanna": "KO",
  "Frysztak Konrad": "KO",
  "Gadowski Krzysztof": "KO",
  "Gajewska Aleksandra": "KO",
  "Gajewska Kinga": "KO",
  "Galemba Leszek": "PiS",
  "Galla Ryszard": "niez.",
  "Gapińska Elżbieta": "KO",
  "Gasiuk-Pihowicz Kamila": "KO",
  "Gawkowski Krzysztof": "Lewica",
  "Gawron Andrzej": "PiS",
  "Gawęda Adam": "PiS",
  "Gaża Grzegorz": "PiS",
  "Gdula Maciej": "Lewica",
  "Gelert Elżbieta": "KO",
  "Gembicka Anna": "PiS",
  "Gill-Piątek Hanna": "Polska2050",
  "Girzyński Zbigniew": "PiS",
  "Giżyński Szymon": "PiS",
  "Glenc Teresa": "PiS",
  "Gliński Piotr": "PiS",
  "Golbik Marta": "KO",
  "Golińska Małgorzata": "PiS",
  "Gonciarz Jarosław": "PiS",
  "Gontarz Robert": "PiS",
  "Gosek Mariusz": "PiS",
  "Gosek-Popiołek Daria": "Lewica",
  "Gosiewska Małgorzata": "PiS",
  "Gowin Jarosław": "PiS",
  "Gołojuch Kazimierz": "PiS",
  "Grabarczyk Cezary": "KO",
  "Grabczuk Krzysztof": "KO",
  "Grabiec Jan": "KO",
  "Gramatyka Michał": "KO",
  "Grupiński Rafał": "KO",
  "Grzyb Andrzej": "KP",
  "Gróbarczyk Marek": "PiS",
  "Gut-Mostowy Andrzej": "PiS",
  "Gwiazdowski Kazimierz": "PiS",
  "Gwóźdź Marcin": "PiS",
  "Górska Agnieszka": "PiS",
  "Górski Maciej": "PiS",
  "Głogowski Tomasz": "KO",
  "Haidar Riad": "KO",
  "Hanajczyk Agnieszka": "KO",
  "Hardie-Douglas Jerzy": "KO",
  "Hartwich Iwona": "KO",
  "Hałas Teresa": "PiS",
  "Hennig-Kloska Paulina": "Polska2050",
  "Hoc Czesław": "PiS",
  "Hoffmann Zbigniew Grzegorz": "PiS",
  "Hok Marek": "KO",
  "Horała Marcin": "PiS",
  "Hreniak Paweł": "PiS",
  "Iwaniak Arkadiusz": "Lewica",
  "Jach Michał": "PiS",
  "Jachira Klaudia": "KO",
  "Janczyk Wiesław": "PiS",
  "Janowska Małgorzata": "PiS",
  "Janyska Maria Małgorzata": "KO",
  "Jaros Michał": "KO",
  "Jaśkowiak Joanna": "KO",
  "Joński Dariusz": "KO",
  "Kaczmarczyk Norbert": "PiS",
  "Kaczyński Filip": "PiS",
  "Kaczyński Jarosław": "PiS",
  "Kaleta Piotr": "PiS",
  "Kaleta Sebastian": "PiS",
  "Kamiński Krystian": "Konfederacja",
  "Kamiński Mariusz": "PiS",
  "Kanthak Jan": "PiS",
  "Kapinos Fryderyk": "PiS",
  "Kasprzak Mieczysław": "KP",
  "Kałużny Mariusz": "PiS",
  "Kidawa-Błońska Małgorzata": "KO",
  "Kierwiński Marcin": "KO",
  "Klimczak Dariusz": "KP",
  "Kluzik-Rostkowska Joanna": "KO",
  "Konieczny Maciej": "Lewica",
  "Konwiński Zbigniew": "KO",
  "Koperski Przemysław": "Lewica",
  "Kopiec Maciej": "Lewica",
  "Korwin-Mikke Janusz": "Konfederacja",
  "Kosiniak-Kamysz Władysław": "KP",
  "Kossakowski Wojciech": "PiS",
  "Kostuś Tomasz": "KO",
  "Kosztowniak Andrzej": "PiS",
  "Kotula Katarzyna": "Lewica",
  "Kowal Paweł": "KO",
  "Kowalczyk Henryk": "PiS",
  "Kowalski Janusz": "PiS",
  "Kownacki Bartosz": "PiS",
  "Kozanecka Ewa": "PiS",
  "Kozik Krzysztof Janusz": "PiS",
  "Kozłowska Iwona Maria": "KO",
  "Kołakowski Lech": "niez.",
  "Kołodziej Ewa": "KO",
  "Krajewski Jarosław": "PiS",
  "Krajewski Stefan": "KP",
  "Krajewski Wiesław": "PiS",
  "Krasulski Leonard": "PiS",
  "Krawczyk Michał": "KO",
  "Kretkowska Katarzyna": "Lewica",
  "Kropiwnicki Robert": "KO",
  "Krupka Anna": "PiS",
  "Krutul Paweł": "Lewica",
  "Kryj Andrzej": "PiS",
  "Krzywonos-Strycharska Henryka": "KO",
  "Krząkała Marek": "KO",
  "Król Piotr": "PiS",
  "Król Wojciech": "KO",
  "Kubiak Marta": "PiS",
  "Kubów Krzysztof": "PiS",
  "Kucharska-Dziedzic Anita": "Lewica",
  "Kuchciński Marek": "PiS",
  "Kukiz Paweł": "Kukiz15",
  "Kulasek Marcin": "Lewica",
  "Kulesza Jakub": "Konfederacja",
  "Kurowska Maria": "PiS",
  "Kurowski Władysław": "PiS",
  "Kurzawa Dariusz": "KP",
  "Kurzępa Jacek": "PiS",
  "Kwiatkowski Robert": "Lewica",
  "Kwiecień Anna": "PiS",
  "Kwitek Marek": "PiS",
  "Lasek Maciej": "KO",
  "Latos Tomasz": "PiS",
  "Lenartowicz Gabriela": "KO",
  "Leniart Ewa": "PiS",
  "Lenz Tomasz": "KO",
  "Leszczyna Izabela": "KO",
  "Lichocka Joanna": "PiS",
  "Lipiec Krzysztof": "PiS",
  "Lipiński Adam": "PiS",
  "Lisiecki Paweł": "PiS",
  "Lorek Grzegorz": "PiS",
  "Lubczyk Radosław": "KP",
  "Lubnauer Katarzyna": "KO",
  "Machałek Marzena": "PiS",
  "Maciejewska Beata": "Lewica",
  "Macierewicz Antoni": "PiS",
  "Maksymowicz Wojciech": "PiS",
  "Malik Ewa": "PiS",
  "Maliszewski Mirosław": "KP",
  "Maląg Marlena Magdalena": "PiS",
  "Marchewka Arkadiusz": "KO",
  "Marczułajtis-Walczak Jagna": "KO",
  "Masłowska Gabriela": "PiS",
  "Materna Jerzy": "PiS",
  "Mateusiak-Pielucha Beata": "PiS",
  "Matusiak Grzegorz": "PiS",
  "Matuszewski Marek": "PiS",
  "Matuszny Kazimierz": "PiS",
  "Matysiak Paulina": "Lewica",
  "Małecki Jerzy": "PiS",
  "Małecki Maciej": "PiS",
  "Michałek Iwona": "PiS",
  "Mieszkowski Krzysztof": "KO",
  "Milczanowska Anna": "PiS",
  "Milewski Daniel": "PiS",
  "Miller Rajmund": "KO",
  "Miszalski Aleksander": "KO",
  "Morawiecki Mateusz": "PiS",
  "Mosiński Jan": "PiS",
  "Moskal Kazimierz": "PiS",
  "Mroczek Czesław": "KO",
  "Mrzygłocka Izabela Katarzyna": "KO",
  "Mrówczyński Aleksander": "PiS",
  "Mucha Joanna": "Polska2050",
  "Mularczyk Arkadiusz": "PiS",
  "Munyama Killion": "KO",
  "Murdzek Wojciech": "PiS",
  "Myrcha Arkadiusz": "KO",
  "Müller Piotr": "PiS",
  "Napieralski Grzegorz": "KO",
  "Neumann Sławomir": "KO",
  "Niedziela Dorota": "KO",
  "Niemczyk Małgorzata": "KO",
  "Nitras Sławomir": "KO",
  "Nowacka Barbara": "KO",
  "Nowak Tomasz Piotr": "KO",
  "Nowicka Danuta": "PiS",
  "Nowicka Wanda": "Lewica",
  "Nowogórska Urszula": "KP",
  "Nykiel Mirosława": "KO",
  "Obaz Robert": "Lewica",
  "Ociepa Marcin": "PiS",
  "Okła-Drewnowicz Marzena": "KO",
  "Olejniczak Waldemar": "PiS",
  "Olichwer Tomasz": "KO",
  "Olszewski Dariusz": "PiS",
  "Olszewski Paweł": "KO",
  "Opioła Marek": "PiS",
  "Osos Katarzyna": "KO",
  "Osuch Jacek": "PiS",
  "Ozdoba Jacek": "PiS",
  "Paluch Anna": "PiS",
  "Pamuła Teresa": "PiS",
  "Papke Paweł": "KO",
  "Paszyk Krzysztof": "KP",
  "Pasławska Urszula": "KP",
  "Paul Jerzy": "PiS",
  "Pawliczak Karolina": "Lewica",
  "Pawłowska Monika": "Lewica",
  "Piecha Bolesław": "PiS",
  "Piechota Sławomir Jan": "KO",
  "Piechowiak Grzegorz": "PiS",
  "Pieczarka Anna": "PiS",
  "Piekarska Katarzyna Maria": "KO",
  "Piontkowski Dariusz": "PiS",
  "Piątkowski Krzysztof": "KO",
  "Plocke Kazimierz": "KO",
  "Pogoda Szymon": "PiS",
  "Polaczek Jerzy": "PiS",
  "Polak Marek": "PiS",
  "Polak Piotr": "PiS",
  "Pomaska Agnieszka": "KO",
  "Poncyljusz Paweł": "KO",
  "Porowska Violetta": "PiS",
  "Porzucek Marcin": "PiS",
  "Prokop-Paczkowska Małgorzata": "Lewica",
  "Protas Jacek": "KO",
  "Protasiewicz Jacek": "KP",
  "Puda Grzegorz": "PiS",
  "Pępek Małgorzata": "KO",
  "Płażyński Kacper": "PiS",
  "Płonka Elżbieta": "PiS",
  "Rau Zbigniew": "PiS",
  "Raś Ireneusz": "KO",
  "Rosa Monika": "KO",
  "Rosati Dariusz": "KO",
  "Rozenek Andrzej": "Lewica",
  "Rusecka Urszula": "PiS",
  "Rusiecki Grzegorz": "KO",
  "Rutka Marek": "Lewica",
  "Rutnicki Jakub": "KO",
  "Rychlik Paweł": "PiS",
  "Rzepa Jarosław": "KP",
  "Rzymkowski Tomasz": "PiS",
  "Rząsa Marek": "KO",
  "Sachajko Jarosław": "Kukiz15",
  "Sak Piotr": "PiS",
  "Sasin Jacek": "PiS",
  "Sawicki Marek": "KP",
  "Saługa Wojciech": "KO",
  "Schetyna Grzegorz": "KO",
  "Scheuring-Wielgus Joanna": "Lewica",
  "Schmidt Anna": "PiS",
  "Schreiber Łukasz": "PiS",
  "Sekuła-Szmajdzińska Małgorzata": "Lewica",
  "Sellin Jarosław": "PiS",
  "Senyszyn Joanna": "Lewica",
  "Siarka Edward": "PiS",
  "Siarkowska Anna Maria": "PiS",
  "Sibińska Krystyna": "KO",
  "Siekierski Czesław": "KP",
  "Siemoniak Tomasz": "KO",
  "Sienkiewicz Bartłomiej": "KO",
  "Sipiera Zdzisław": "PiS",
  "Skowrońska Krystyna": "KO",
  "Skwarek Sławomir": "PiS",
  "Smoliński Kazimierz": "PiS",
  "Sobolewski Krzysztof": "PiS",
  "Soboń Artur": "PiS",
  "Soin Agnieszka": "PiS",
  "Sonik Bogusław": "KO",
  "Sowa Marek": "KO",
  "Sowińska Anita": "Lewica",
  "Sośnierz Andrzej": "PiS",
  "Sośnierz Dobromir": "Konfederacja",
  "Sroka Magdalena": "PiS",
  "Stachowiak-Różecka Mirosława": "PiS",
  "Stefaniuk Dariusz": "PiS",
  "Sterczewski Franciszek": "KO",
  "Strzałka Beata": "PiS",
  "Suchoń Mirosław": "KO",
  "Suski Marek": "PiS",
  "Szarama Wojciech": "PiS",
  "Szałabawka Artur": "PiS",
  "Szczepański Wiesław": "Lewica",
  "Szczerba Michał": "KO",
  "Szczudło Aleksandra": "PiS",
  "Szczurek-Żelazko Józefa": "PiS",
  "Szefernaker Paweł": "PiS",
  "Szejna Andrzej": "Lewica",
  "Szewiński Andrzej": "KO",
  "Szlachta Andrzej": "PiS",
  "Szopiński Jan": "Lewica",
  "Szramka Paweł": "Kukiz15",
  "Szulowski Krzysztof": "PiS",
  "Szumilas Krystyna": "KO",
  "Szumowski Łukasz": "PiS",
  "Szwed Stanisław": "PiS",
  "Szymańska Ewa": "PiS",
  "Szymański Tomasz": "KO",
  "Szynkowski vel Sęk Szymon": "PiS",
  "Szłapka Adam": "KO",
  "Sójka Katarzyna": "PiS",
  "Sługocki Waldemar": "KO",
  "Tarczyński Dominik": "PiS",
  "Tchórzewski Krzysztof": "PiS",
  "Telus Robert": "PiS",
  "Terlecki Ryszard": "PiS",
  "Tomaszewski Tadeusz": "Lewica",
  "Tomaszewski Włodzimierz": "PiS",
  "Tomczak Jacek": "KP",
  "Tomczyk Cezary": "KO",
  "Tracz Małgorzata": "KO",
  "Trela Tomasz": "Lewica",
  "Trepka Mariusz": "PiS",
  "Truskolaski Krzysztof": "KO",
  "Tuduj Krzysztof": "Konfederacja",
  "Tułajew Sylwester": "PiS",
  "Tyszka Stanisław": "Kukiz15",
  "Tyszkiewicz Robert": "KO",
  "Ueberhan Katarzyna": "Lewica",
  "Urbaniak Jarosław": "KO",
  "Urbaniak Michał": "Konfederacja",
  "Uruski Piotr": "PiS",
  "Uściński Piotr": "PiS",
  "Warchoł Marcin": "PiS",
  "Wargocka Teresa": "PiS",
  "Warwas Robert": "PiS",
  "Warzecha Jan": "PiS",
  "Wasilewska Anna": "KO",
  "Wassermann Małgorzata": "PiS",
  "Wawrzyk Piotr": "PiS",
  "Wałęsa Jarosław": "KO",
  "Wcisło Marta": "KO",
  "Weber Rafał": "PiS",
  "Wesoły Marek": "PiS",
  "Wicher Patryk": "PiS",
  "Wieczorek Dariusz": "Lewica",
  "Wielichowska Monika": "KO",
  "Wilczyński Ryszard": "KO",
  "Wilk Jerzy": "PiS",
  "Winnicki Robert": "Konfederacja",
  "Witczak Mariusz": "KO",
  "Witek Elżbieta": "PiS",
  "Wojciechowski Grzegorz": "PiS",
  "Wojtyszek Agata Katarzyna": "PiS",
  "Wolski Zdzisław": "Lewica",
  "Wontor Bogusław": "Lewica",
  "Woś Michał": "PiS",
  "Woźniak Grzegorz Adam": "PiS",
  "Woźniak Tadeusz": "PiS",
  "Wróblewski Bartłomiej": "PiS",
  "Wypij Michał": "PiS",
  "Wójcik Michał": "PiS",
  "Wąsik Maciej": "PiS",
  "Zagórski Marek": "PiS",
  "Zalewski Paweł": "KO",
  "Zandberg Adrian": "Lewica",
  "Zawisza Marcelina": "Lewica",
  "Zawiślak Sławomir": "PiS",
  "Zembaczyński Witold": "KO",
  "Zgorzelski Piotr": "KP",
  "Ziejewski Zbigniew": "KP",
  "Zielińska Urszula": "KO",
  "Zieliński Jarosław": "PiS",
  "Zieliński Tomasz": "PiS",
  "Zientarski Piotr Benedykt": "KO",
  "Zimoch Tomasz": "KO",
  "Ziobro Zbigniew": "PiS",
  "Zubowski Wojciech": "PiS",
  "Zwiefka Tadeusz": "KO",
  "Zyska Ireneusz": "PiS",
  "Ławniczak Tomasz": "PiS",
  "Łopata Jan": "KP",
  "Łośko Magdalena": "KO",
  "Łącki Artur": "KO",
  "Ścigaj Agnieszka": "niez.",
  "Śledzińska-Katarasińska Iwona": "KO",
  "Śmiszek Krzysztof": "Lewica",
  "Śniadek Janusz": "PiS",
  "Śnieżek Adam": "PiS",
  "Świat Jacek": "PiS",
  "Żalek Jacek": "PiS",
  "Żelazowska Bożena": "KP",
  "Żuk Stanisław": "Kukiz15",
  "Żukowska Anna Maria": "Lewica"
}